django_rest_slack-0.4.dist-info/DESCRIPTION.rst
django_rest_slack-0.4.dist-info/METADATA
django_rest_slack-0.4.dist-info/RECORD
django_rest_slack-0.4.dist-info/WHEEL
django_rest_slack-0.4.dist-info/metadata.json
django_rest_slack-0.4.dist-info/top_level.txt
rest_slack/__init__.py
rest_slack/app_settings.py
rest_slack/models.py
rest_slack/registry.py
rest_slack/tests.py
rest_slack/utils.py
rest_slack/views.py
