Metadata-Version: 2.0
Name: django-rest-slack
Version: 0.4
Summary: A simple, reusable Django app for handling and storing Slack events and slash commands.
Home-page: https://github.com/erm/django-rest-slack/
Author: Jordan E.
Author-email: jermff@gmail.com
License: MIT License
Platform: UNKNOWN
Classifier: Environment :: Web Environment
Classifier: Framework :: Django
Classifier: Framework :: Django :: 2.0
Classifier: Intended Audience :: Developers
Classifier: License :: OSI Approved :: MIT License
Classifier: Operating System :: OS Independent
Classifier: Programming Language :: Python
Classifier: Programming Language :: Python :: 3.5
Classifier: Programming Language :: Python :: 3.6
Classifier: Topic :: Internet :: WWW/HTTP
Classifier: Topic :: Internet :: WWW/HTTP :: Dynamic Content
